{
"dest_language": "English",
"is_add_src": 0,
"is_add_transliteration": 0,
"src_language": "Spanish",
"text_lines": "Si V - ser uve  - bu sonar\nbebé\nbaso\nalimentación botella\nvino\nbicicleta\nviento c=θ\n\nel carta h (nenver pronunciado)\nHelena\nhospital\nhotel\nhijos  ihos\n\nla letras pero 1 sonido - ch \nchachacha\nleche\nchica\nocho\nchurro\n",
"translated_text": "Yes V - be vee  - bu sound\nbaby\nbaso\nfeeding bottle\ncame\nbike\nwind c=θ\n\nhe letter h (nenver pronounced)\nHelena\nhospital\nhotel\nsons  ihos\n\nthe letters but 1 sound - ch \ncha cha cha\nmilk\ngirl\neight\nfried dough\n"
}